monarchmoney/__init__.py
monarchmoney/error_handlers.py
monarchmoney/exceptions.py
monarchmoney/logging_config.py
monarchmoney/monarchmoney.py
monarchmoney/optimizations.py
monarchmoney/session_storage.py
monarchmoney/validators.py
monarchmoney/graphql/__init__.py
monarchmoney/graphql/cache.py
monarchmoney/graphql/fragments.py
monarchmoney/graphql/investment_operations.py
monarchmoney/graphql/query_builder.py
monarchmoney/graphql/query_variants.py
monarchmoney/graphql/robust_operation.py
monarchmoney/services/__init__.py
monarchmoney/services/account_service.py
monarchmoney/services/authentication_service.py
monarchmoney/services/base_service.py
monarchmoney/services/budget_service.py
monarchmoney/services/graphql_client.py
monarchmoney/services/insight_service.py
monarchmoney/services/investment_service.py
monarchmoney/services/settings_service.py
monarchmoney/services/transaction_service.py
monarchmoney_enhanced-0.10.1.dist-info/licenses/LICENSE
monarchmoney_enhanced-0.10.1.dist-info/METADATA
monarchmoney_enhanced-0.10.1.dist-info/WHEEL
monarchmoney_enhanced-0.10.1.dist-info/top_level.txt
monarchmoney_enhanced-0.10.1.dist-info/RECORD
