Metadata-Version: 2.4
Name: monarchmoney-enhanced
Version: 0.10.1
Summary: Enhanced Monarch Money API with bulk transaction operations, GraphQL optimizations, intelligent caching, query variants, and service-oriented architecture
Home-page: https://github.com/keithah/monarchmoney-enhanced
Author: keithah
Author-email: keithah <keithah@users.noreply.github.com>
License: MIT
Project-URL: Homepage, https://github.com/keithah/monarchmoney-enhanced
Project-URL: Repository, https://github.com/keithah/monarchmoney-enhanced
Keywords: monarch money,financial,money,personal finance
Platform: any
Classifier: Development Status :: 4 - Beta
Classifier: Intended Audience :: Developers
Classifier: Intended Audience :: Financial and Insurance Industry
Classifier: License :: OSI Approved :: MIT License
Classifier: Topic :: Office/Business :: Financial
License-File: LICENSE
Requires-Dist: aiohttp>=3.8.4
Requires-Dist: gql>=3.4
Requires-Dist: oathtool>=2.3.1
Requires-Dist: cryptography>=3.4.8
Dynamic: author
Dynamic: home-page
Dynamic: license-file
Dynamic: platform
